proxy/__init__.py
proxy/proxy.py
proxy/py.typed
tests/__init__.py
tests/test_proxy.py
typed_proxy-1.0.1.dist-info/LICENSE
typed_proxy-1.0.1.dist-info/METADATA
typed_proxy-1.0.1.dist-info/WHEEL
typed_proxy-1.0.1.dist-info/top_level.txt
typed_proxy-1.0.1.dist-info/RECORD
