Metadata-Version: 2.1
Name: typed-proxy
Version: 1.0.1
Summary: A Python package that provides a metaclass for creating proxy classes with type annotations.
Home-page: https://github.com/jonghwanhyeon/typed-proxy
Author: Jonghwan Hyeon
Author-email: jonghwanhyeon93@gmail.com
License: MIT
Keywords: metaclass,proxy
Classifier: Development Status :: 4 - Beta
Classifier: Intended Audience :: Developers
Classifier: License :: OSI Approved :: MIT License
Classifier: Programming Language :: Python :: 3
Classifier: Programming Language :: Python :: 3 :: Only
Requires-Python: >=3.7
License-File: LICENSE
Provides-Extra: dev
Requires-Dist: pytest ; extra == 'dev'
Requires-Dist: black ; extra == 'dev'
Requires-Dist: griffe-generics ; extra == 'dev'
Requires-Dist: griffe-modernized-annotations ; extra == 'dev'
Requires-Dist: mkdocs ; extra == 'dev'
Requires-Dist: mkdocs-material ; extra == 'dev'
Requires-Dist: mkdocstrings[python] ; extra == 'dev'
Requires-Dist: mypy ; extra == 'dev'
Requires-Dist: rich ; extra == 'dev'
Requires-Dist: ruff ; extra == 'dev'
Provides-Extra: docs
Requires-Dist: black ; extra == 'docs'
Requires-Dist: griffe-generics ; extra == 'docs'
Requires-Dist: griffe-modernized-annotations ; extra == 'docs'
Requires-Dist: mkdocs ; extra == 'docs'
Requires-Dist: mkdocs-material ; extra == 'docs'
Requires-Dist: mkdocstrings[python] ; extra == 'docs'
Provides-Extra: tests
Requires-Dist: pytest ; extra == 'tests'
